MANIFEST.in
README.rst
pyxontime-cli.py
pyxontime-gui.py
setup.py
pyxontime/__init__.py
pyxontime/oxontime.py
pyxontime/persist.py
pyxontime.egg-info/PKG-INFO
pyxontime.egg-info/SOURCES.txt
pyxontime.egg-info/dependency_links.txt
pyxontime.egg-info/requires.txt
pyxontime.egg-info/top_level.txt
pyxontime/cli/__init__.py
pyxontime/cli/search.py
pyxontime/cli/store.py