Metadata-Version: 1.0
Name: pyxontime
Version: 0.3
Summary: Python software to get OXONTIME's bus schedules of Oxfordshire
Home-page: UNKNOWN
Author: Arnaud Bos
Author-email: arnaud.tlse@gmail.com
License: UNKNOWN
Platform: UNKNOWN
